mergetbapi/__init__.py
mergetbapi/google/__init__.py
mergetbapi/google/api/__init__.py
mergetbapi/grpc/__init__.py
mergetbapi/grpc/gateway/__init__.py
mergetbapi/grpc/gateway/protoc_gen_openapiv2/__init__.py
mergetbapi/grpc/gateway/protoc_gen_openapiv2/options/__init__.py
mergetbapi/portal/__init__.py
mergetbapi/portal/v1/__init__.py
mergetbapi/reconcile/__init__.py
mergetbapi/validator/__init__.py
mergetbapi/xir/__init__.py
mergetbapi-1.3.50.dist-info/licenses/LICENSE.md
mergetbapi-1.3.50.dist-info/METADATA
mergetbapi-1.3.50.dist-info/WHEEL
mergetbapi-1.3.50.dist-info/top_level.txt
mergetbapi-1.3.50.dist-info/RECORD
