Metadata-Version: 2.4
Name: mergetbapi
Version: 1.3.50
Summary: Client interface to the MergeTB API
Home-page: https://gitlab.com/mergetb/api
Author: Brian Kocoloski
Author-email: bkocolos@isi.edu
License: MIT
Classifier: Programming Language :: Python :: 3
Classifier: License :: OSI Approved :: MIT License
Classifier: Operating System :: OS Independent
Classifier: Intended Audience :: Developers
Classifier: Intended Audience :: End Users/Desktop
Classifier: Development Status :: 4 - Beta
Requires-Python: >=3
License-File: LICENSE.md
Requires-Dist: betterproto>=2.0.0b6
Requires-Dist: grpclib>=0.4.7
Dynamic: author
Dynamic: author-email
Dynamic: classifier
Dynamic: description
Dynamic: description-content-type
Dynamic: home-page
Dynamic: license
Dynamic: license-file
Dynamic: requires-dist
Dynamic: requires-python
Dynamic: summary
